libspwn-1.0.data/scripts/libspwn
src/libspwn/__init__.py
src/libspwn/__main__.py
libspwn-1.0.dist-info/LICENSE
libspwn-1.0.dist-info/METADATA
libspwn-1.0.dist-info/WHEEL
libspwn-1.0.dist-info/top_level.txt
libspwn-1.0.dist-info/RECORD
